{
  "id": "email_008235",
  "folder": "Principio del archivo de datos de Outlook/DEPURADOS",
  "extraction_date": "2025-09-19T12:27:49.362325",
  "subject": "🌎 Conexión regional: hablemos de ética con Eduardo Infante 🧠",
  "sender_name": "SURA Corporativo",
  "delivery_time": "2025-08-05T16:50:17.711510",
  "creation_time": "2025-08-05T16:59:38.025651",
  "modification_time": "2025-08-05T16:59:39.740796",
  "eml_file": "emails/email_008235.eml",
  "attachments": [],
  "plain_text_length": 0,
  "html_content_length": 1991
}