{
  "id": "email_000302",
  "folder": "Principio del archivo de datos de Outlook/ASIGNADOS",
  "extraction_date": "2025-09-19T12:24:42.915108",
  "subject": "RV: COLEGIO SUMMERHILL COTIZACIÓN RENOVACIÓN 2 605 20002373 AGENTE 479",
  "sender_name": "Mesa Puebla",
  "delivery_time": "2025-08-05T17:40:41.169271",
  "creation_time": "2025-08-06T03:16:32.745415",
  "modification_time": "2025-08-06T03:16:50.228854",
  "attachment_count": 2,
  "eml_file": "emails/email_000302.eml",
  "attachments": [
    {
      "filename": "attachment_0",
      "size": 62746,
      "path": "attachments/email_000302/attachment_0"
    },
    {
      "filename": "attachment_1",
      "size": 3958,
      "path": "attachments/email_000302/attachment_1"
    }
  ],
  "plain_text_length": 0,
  "html_content_length": 21413
}