{
  "id": "email_008590",
  "folder": "Principio del archivo de datos de Outlook/DEPURADOS",
  "extraction_date": "2025-09-19T12:27:53.742873",
  "subject": "OF1 / Motor / 2527385 / 003032 / RENOVACION-INDIVIDUAL",
  "sender_name": "brightside.rsa@segurossura.com.mx",
  "delivery_time": "2025-08-19T17:41:34.006412",
  "creation_time": "2025-08-19T17:41:33.794446",
  "modification_time": "2025-08-19T17:41:39.060131",
  "eml_file": "emails/email_008590.eml",
  "attachments": [],
  "plain_text_length": 0,
  "html_content_length": 2096
}