{
  "id": "email_004200",
  "folder": "Principio del archivo de datos de Outlook/PRODUCCION ",
  "extraction_date": "2025-09-19T12:26:15.207759",
  "subject": "LEONARDO DANIEL MUJICA ENRIQUEZ / poliza ALA AZUL OFICINA 1 RAMO 606 POLIZA -21330  ",
  "sender_name": "Diana Salinas Colin",
  "delivery_time": "2025-08-04T19:12:30.125005",
  "creation_time": "2025-08-06T14:19:35.208570",
  "modification_time": "2025-08-06T14:28:51.773413",
  "eml_file": "emails/email_004200.eml",
  "attachments": [],
  "plain_text_length": 0,
  "html_content_length": 4268
}