{
  "id": "email_007086",
  "folder": "Principio del archivo de datos de Outlook/PRODUCCION ",
  "extraction_date": "2025-09-19T12:27:26.498100",
  "subject": "RE: COTIZACION RC ARRENDATARIO ",
  "sender_name": "Cruz Aguila Xenia Cecilia",
  "delivery_time": "2025-08-15T19:17:20.362659",
  "creation_time": "2025-08-15T19:53:03.697471",
  "modification_time": "2025-08-15T19:53:54.756292",
  "eml_file": "emails/email_007086.eml",
  "attachments": [],
  "plain_text_length": 0,
  "html_content_length": 0
}