{
  "id": "email_004857",
  "folder": "Principio del archivo de datos de Outlook/PRODUCCION ",
  "extraction_date": "2025-09-19T12:26:30.515228",
  "subject": "Re: SOLICITUD CARTA VIGENCIAS SUPOLLO/ 211/ 7761 ADAN PORRAS",
  "sender_name": "Paola Padilla",
  "delivery_time": "2025-08-04T14:47:57.438536",
  "creation_time": "2025-08-04T23:40:14.400735",
  "modification_time": "2025-08-04T18:35:44.780237",
  "attachment_count": 1,
  "eml_file": "emails/email_004857.eml",
  "attachments": [
    {
      "filename": "attachment_0",
      "size": 276493,
      "path": "attachments/email_004857/attachment_0"
    }
  ],
  "plain_text_length": 0,
  "html_content_length": 5829
}